umlmodel/Actor.py
umlmodel/BaseAttributes.py
umlmodel/Class.py
umlmodel/ClassCommon.py
umlmodel/Field.py
umlmodel/FieldType.py
umlmodel/Interface.py
umlmodel/Link.py
umlmodel/LinkedObject.py
umlmodel/Method.py
umlmodel/ModelTypes.py
umlmodel/Modifier.py
umlmodel/Note.py
umlmodel/Parameter.py
umlmodel/ParameterType.py
umlmodel/ReturnType.py
umlmodel/SDInstance.py
umlmodel/SDMessage.py
umlmodel/Text.py
umlmodel/UmlType.py
umlmodel/UseCase.py
umlmodel/__init__.py
umlmodel/_version.py
umlmodel/py.typed
umlmodel/enumerations/DisplayMethods.py
umlmodel/enumerations/DisplayParameters.py
umlmodel/enumerations/LinkType.py
umlmodel/enumerations/Stereotype.py
umlmodel/enumerations/Visibility.py
umlmodel/enumerations/__init__.py
umlmodel/enumerations/py.typed
umlmodel-3.3.0.dist-info/licenses/LICENSE
umlmodel-3.3.0.dist-info/METADATA
umlmodel-3.3.0.dist-info/WHEEL
umlmodel-3.3.0.dist-info/entry_points.txt
umlmodel-3.3.0.dist-info/top_level.txt
umlmodel-3.3.0.dist-info/RECORD
