Metadata-Version: 2.4
Name: umlmodel
Version: 3.3.0
Summary: The data model for UML Diagrams
Author-email: "Humberto A. Sanchez II" <Humberto.A.Sanchez.II@gmail.com>
Maintainer-email: "Humberto A. Sanchez II" <Humberto.A.Sanchez.II@gmail.com>
License-Expression: AGPL-1.0-or-later
Project-URL: Repository, https://github.com/hasii2011/umlmodel
Keywords: umldiagrammer,python,data model
Classifier: Programming Language :: Python
Classifier: Intended Audience :: Developers
Classifier: Operating System :: MacOS :: MacOS X
Classifier: Topic :: Software Development :: Libraries :: Python Modules
License-File: LICENSE
Requires-Dist: human_id==0.2.0
Provides-Extra: test
Requires-Dist: mypy==1.18.2; extra == "test"
Requires-Dist: mypy-extensions==1.1.0; extra == "test"
Requires-Dist: types-Deprecated==1.2.9.20240311; extra == "test"
Requires-Dist: html-testRunner~=1.2.1; extra == "test"
Requires-Dist: codeallybasic==1.10.4; extra == "test"
Provides-Extra: deploy
Requires-Dist: wheel==0.45.1; extra == "deploy"
Requires-Dist: setuptools==80.9.0; extra == "deploy"
Requires-Dist: twine==6.1.0; extra == "deploy"
Requires-Dist: build==1.2.2.post1; extra == "deploy"
Requires-Dist: pkginfo==1.12.1.2; extra == "deploy"
Dynamic: license-file
